cuvarbase/__init__.py
cuvarbase/bls.py
cuvarbase/ce.py
cuvarbase/core.py
cuvarbase/cunfft.py
cuvarbase/lombscargle.py
cuvarbase/pdm.py
cuvarbase/utils.py
cuvarbase/kernels/bls.cu
cuvarbase/kernels/ce.cu
cuvarbase/kernels/cunfft.cu
cuvarbase/kernels/lomb.cu
cuvarbase/kernels/pdm.cu
cuvarbase/kernels/wavelet.cu
cuvarbase/tests/__init__.py
cuvarbase/tests/test_bls.py
cuvarbase/tests/test_ce.py
cuvarbase/tests/test_lombscargle.py
cuvarbase/tests/test_nfft.py
cuvarbase/tests/test_pdm.py
cuvarbase-0.2.5.dist-info/LICENSE.txt
cuvarbase-0.2.5.dist-info/METADATA
cuvarbase-0.2.5.dist-info/WHEEL
cuvarbase-0.2.5.dist-info/top_level.txt
cuvarbase-0.2.5.dist-info/RECORD
