Metadata-Version: 2.1
Name: cuvarbase
Version: 0.2.5
Summary: Period-finding and variability on the GPU
Home-page: https://github.com/johnh2o2/cuvarbase
Author: John Hoffman
Author-email: johnh2o2@gmail.com
License: UNKNOWN
Platform: UNKNOWN
Classifier: Development Status :: 4 - Beta
Classifier: Environment :: Console
Classifier: Intended Audience :: Science/Research
Classifier: License :: OSI Approved :: GNU General Public License v3 (GPLv3)
Classifier: Natural Language :: English
Classifier: Programming Language :: Python :: 2.7
Classifier: Programming Language :: Python :: 3.4
Classifier: Programming Language :: Python :: 3.5
Classifier: Programming Language :: Python :: 3.6
Classifier: Programming Language :: C
Classifier: Programming Language :: C++
Requires-Dist: future
Requires-Dist: numpy (>=1.6)
Requires-Dist: scipy
Requires-Dist: pycuda (>=2017.1.1)
Requires-Dist: scikit-cuda
